scripts
shell2
