Metadata-Version: 2.1
Name: shell2
Version: 0.103
Summary: UNKNOWN
Home-page: UNKNOWN
License: UNKNOWN
Platform: UNKNOWN
